phos/__init__.py
phos/datatypes.py
phos/mapper.py
phos/parser.py
phos/utils.py
phos-0.0.1.dist-info/LICENSE
phos-0.0.1.dist-info/METADATA
phos-0.0.1.dist-info/WHEEL
phos-0.0.1.dist-info/top_level.txt
phos-0.0.1.dist-info/RECORD
