Metadata-Version: 2.1
Name: phos
Version: 0.0.1
Summary: This is a raw8 parser
Home-page: https://github.com/karampitsos/light
Author: Nikolaos Karampitsos
Author-email: nikolaos.karampitsos@gmail.com
License: MIT License
Classifier: Programming Language :: Python :: 3
Classifier: License :: OSI Approved :: MIT License
Classifier: Operating System :: OS Independent
Requires-Python: >=3.7
License-File: LICENSE
Provides-Extra: dev
Requires-Dist: pytest (>=3.7) ; extra == 'dev'
